mihcsme_py/writer.py
mihcsme_py/cli.py
mihcsme_py/omero_connection.py
mihcsme_py/uploader.py
mihcsme_py/parser.py
mihcsme_py/__init__.py
mihcsme_py/models.py
mihcsme_py-0.1.1.dist-info/WHEEL
mihcsme_py-0.1.1.dist-info/entry_points.txt
mihcsme_py-0.1.1.dist-info/METADATA
mihcsme_py-0.1.1.dist-info/RECORD
