Metadata-Version: 2.3
Name: mihcsme-py
Version: 0.1.1
Summary: Convert MIHCSME metadata from Excel to Pydantic model and upload to OMERO
Keywords: OMERO,MIHCSME,metadata,microscopy,high-content-screening
Author: Maarten Paul
Author-email: Maarten Paul <m.w.paul@lacdr.leidenuniv.nl>
License:                                  Apache License
Classifier: Development Status :: 3 - Alpha
Classifier: Intended Audience :: Science/Research
Classifier: License :: OSI Approved :: MIT License
Classifier: Operating System :: OS Independent
Classifier: Programming Language :: Python :: 3
Classifier: Programming Language :: Python :: 3.9
Classifier: Programming Language :: Python :: 3.10
Classifier: Programming Language :: Python :: 3.11
Classifier: Programming Language :: Python :: 3.12
Classifier: Topic :: Scientific/Engineering :: Bio-Informatics
Requires-Dist: pandas>=2.0.0
Requires-Dist: pydantic>=2.0.0
Requires-Dist: openpyxl>=3.1.0
Requires-Dist: typer>=0.9.0 ; extra == 'all'
Requires-Dist: rich>=13.0.0 ; extra == 'all'
Requires-Dist: typer>=0.9.0 ; extra == 'cli'
Requires-Dist: rich>=13.0.0 ; extra == 'cli'
Requires-Dist: pytest>=7.0.0 ; extra == 'dev'
Requires-Dist: pytest-cov>=4.0.0 ; extra == 'dev'
Requires-Dist: black>=23.0.0 ; extra == 'dev'
Requires-Dist: ruff>=0.1.0 ; extra == 'dev'
Requires-Dist: mypy>=1.0.0 ; extra == 'dev'
Requires-Dist: ipython>=8.0.0 ; extra == 'dev'
Requires-Dist: mkdocs>=1.5.0 ; extra == 'docs'
Requires-Dist: mkdocs-material>=9.0.0 ; extra == 'docs'
Requires-Dist: mkdocstrings[python]>=0.24.0 ; extra == 'docs'
Requires-Dist: mkdocs-gen-files>=0.5.0 ; extra == 'docs'
Requires-Dist: mkdocs-section-index>=0.3.0 ; extra == 'docs'
Requires-Dist: griffe-pydantic>=0.2.0 ; extra == 'docs'
Requires-Dist: llm>=0.19 ; extra == 'llm'
Requires-Dist: omero-py>=5.19.0 ; extra == 'omero'
Requires-Python: >=3.9
Project-URL: Homepage, https://github.com/Leiden-Cell-Observatory/MIHCSME_OMERO
Project-URL: Issues, https://github.com/Leiden-Cell-Observatory/MIHCSME_OMERO/issues
Project-URL: Repository, https://github.com/Leiden-Cell-Observatory/MIHCSME_OMERO
Provides-Extra: all
Provides-Extra: cli
Provides-Extra: dev
Provides-Extra: docs
Provides-Extra: llm
Provides-Extra: omero
